[
    {
        "title": "Baahubali: The Beginning",
        "description": "A man destined for greatness uncovers his royal lineage and seeks revenge.",
        "date": "2015-07-10"
    },
    {
        "title": "Baahubali: The Conclusion",
        "description": "The son of a fallen prince returns to claim his rightful place in Mahishmati.",
        "date": "2017-04-28"
    },
    {
        "title": "Geetha Govindam",
        "description": "A young lecturer tries to win over a woman who mistakenly perceives him as a flirt.",
        "date": "2018-08-15"
    },
    {
        "title": "Athadu",
        "description": "An assassin on the run finds himself entangled with a family that mistakes him for their lost son.",
        "date": "2005-08-10"
    },
    {
        "title": "Pokiri",
        "description": "An undercover cop infiltrates the mafia and fights to eliminate crime.",
        "date": "2006-04-28"
    },
    {
        "title": "Magadheera",
        "description": "Reincarnation brings two lovers together, bound by a centuries-old bond.",
        "date": "2009-07-31"
    },
    {
        "title": "Srimanthudu",
        "description": "A billionaire adopts a village and fights to improve the lives of its people.",
        "date": "2015-08-07"
    },
    {
        "title": "Bharat Ane Nenu",
        "description": "An NRI reluctantly becomes chief minister and vows to reform his state.",
        "date": "2018-04-20"
    },
    {
        "title": "Rangasthalam",
        "description": "A hearing-impaired villager stands up against a corrupt leader.",
        "date": "2018-03-30"
    },
    {
        "title": "Arya",
        "description": "A young man pursues his love interest, showcasing the power of pure love.",
        "date": "2004-05-07"
    }
]
